bunker/__init__.py
bunker/buildbunker.py
bunker/bunker.py
bunker/common.py
bunker/emergency.py
bunker/extras.py
bunker/ignore.py
bunker/init.py
bunker/install.py
bunker/prompt.py
bunker/repo.py
bunker/test.py
aws_bunker-0.4.5.dist-info/LICENSE
aws_bunker-0.4.5.dist-info/METADATA
aws_bunker-0.4.5.dist-info/WHEEL
aws_bunker-0.4.5.dist-info/entry_points.txt
aws_bunker-0.4.5.dist-info/top_level.txt
aws_bunker-0.4.5.dist-info/RECORD
