Metadata-Version: 2.1
Name: aws-bunker
Version: 0.4.5
Summary: bunker is a command line program for setting up an ec2 in AWS for remote development or as a backup. It can clone your git repos, and transfer ignored files from your machine to the ec2.
Home-page: https://gitlab.com/shindagger/bunker
Author: Andy Klier, Gus Clemens
Author-email: andyklier@gmail.com
License: UNKNOWN
Platform: UNKNOWN
Classifier: Programming Language :: Python :: 3
Classifier: License :: OSI Approved :: MIT License
Classifier: Operating System :: OS Independent
Requires-Dist: setuptools
Requires-Dist: boto3
Requires-Dist: inquirer
Requires-Dist: paramiko
Requires-Dist: tqdm
